[
    {
        "firstName": "Francis",
        "lastName": "Brown",
        "age": 38,
        "address": {
            "streetAddress": "66627 Fredric Via",
            "city": "Wilkinsonport",
            "state": "Connecticut",
            "postalCode": 76602
        },
        "phoneNumbers": [
            {
                "type": "Fax",
                "number": "(505) 250-6368"
            },
            {
                "type": "Work",
                "number": "(586) 650-0945"
            }
        ]
    },
    {
        "firstName": "Lashawnda",
        "lastName": "Altenwerth",
        "age": 21,
        "address": {
            "streetAddress": "000 Borer Bypass",
            "city": "West Tuan",
            "state": "Michigan",
            "postalCode": 13938
        },
        "phoneNumbers": [
            {
                "type": "Home",
                "number": "(983) 428-2340"
            },
            {
                "type": "Home",
                "number": "(920) 369-4051"
            }
        ]
    },
    {
        "firstName": "Cristobal",
        "lastName": "Breitenberg",
        "age": 57,
        "address": {
            "streetAddress": "91200 Aufderhar Ramp",
            "city": "Louport",
            "state": "Idaho",
            "postalCode": 24986
        },
        "phoneNumbers": [
            {
                "type": "Work",
                "number": "(730) 643-6960"
            },
            {
                "type": "Work",
                "number": "(763) 394-4248"
            },
            {
                "type": "Work",
                "number": "(505) 628-1399"
            }
        ]
    },
    {
        "firstName": "Ellen",
        "lastName": "Greenholt",
        "age": 32,
        "address": {
            "streetAddress": "04701 Candy Viaduct",
            "city": "Sherylport",
            "state": "Nebraska",
            "postalCode": 89465
        },
        "phoneNumbers": [
            {
                "type": "Work",
                "number": "(281) 312-1595"
            },
            {
                "type": "Fax",
                "number": "(505) 644-3103"
            }
        ]
    },
    {
        "firstName": "Daren",
        "lastName": "Mitchell",
        "age": 59,
        "address": {
            "streetAddress": "01143 Rolland Island",
            "city": "North Norbertoborough",
            "state": "Delaware",
            "postalCode": 35957
        },
        "phoneNumbers": [
            {
                "type": "Home",
                "number": "(730) 242-2649"
            },
            {
                "type": "Home",
                "number": "(305) 206-1764"
            },
            {
                "type": "Home",
                "number": "(754) 684-0389"
            }
        ]
    },
    {
        "firstName": "Emmanuel",
        "lastName": "Boehm",
        "age": 32,
        "address": {
            "streetAddress": "87322 Klein Pike",
            "city": "Giselestad",
            "state": "Indiana",
            "postalCode": 23023
        },
        "phoneNumbers": [
        ]
    },
    {
        "firstName": "Emilia",
        "lastName": "Deckow",
        "age": 34,
        "address": {
            "streetAddress": "93992 Britney Place",
            "city": "Tarynburgh",
            "state": "Arizona",
            "postalCode": 5108
        },
        "phoneNumbers": [
        ]
    },
    {
        "firstName": "Tristan",
        "lastName": "Ernser",
        "age": 57,
        "address": {
            "streetAddress": "58318 Cormier Terrace",
            "city": "New Keshia",
            "state": "Louisiana",
            "postalCode": 10996
        },
        "phoneNumbers": [
            {
                "type": "Fax",
                "number": "(730) 222-9477"
            }
        ]
    },
    {
        "firstName": "Lorrine",
        "lastName": "Stamm",
        "age": 25,
        "address": {
            "streetAddress": "525 Maribel Divide",
            "city": "Stoltenbergstad",
            "state": "Maine",
            "postalCode": 97556
        },
        "phoneNumbers": [
            {
                "type": "Fax",
                "number": "(305) 250-7225"
            }
        ]
    },
    {
        "firstName": "Vernie",
        "lastName": "Lakin",
        "age": 55,
        "address": {
            "streetAddress": "096 Haley Burg",
            "city": "Lake Ivory",
            "state": "Hawaii",
            "postalCode": 57078
        },
        "phoneNumbers": [
            {
                "type": "Work",
                "number": "(505) 648-6394"
            },
            {
                "type": "Fax",
                "number": "(505) 644-5393"
            }
        ]
    }
]